cycler/__init__.py
cycler-0.12.0.dist-info/LICENSE
cycler-0.12.0.dist-info/METADATA
cycler-0.12.0.dist-info/WHEEL
cycler-0.12.0.dist-info/top_level.txt
cycler-0.12.0.dist-info/RECORD
