Metadata-Version: 2.1
Name: cycler
Version: 0.12.0
Summary: Composable style cycles
Author-email: Thomas A Caswell <matplotlib-users@python.org>
License: Copyright (c) 2015, matplotlib project
Project-URL: homepage, https://matplotlib.org/cycler/
Project-URL: repository, https://github.com/matplotlib/cycler
Keywords: cycle kwargs
Classifier: License :: OSI Approved :: BSD License
Classifier: Development Status :: 4 - Beta
Classifier: Programming Language :: Python :: 3
Classifier: Programming Language :: Python :: 3.8
Classifier: Programming Language :: Python :: 3.9
Classifier: Programming Language :: Python :: 3.10
Classifier: Programming Language :: Python :: 3.11
Classifier: Programming Language :: Python :: 3.12
Classifier: Programming Language :: Python :: 3 :: Only
Requires-Python: >=3.8
License-File: LICENSE
Provides-Extra: docs
Requires-Dist: ipython; extra == "docs"
Requires-Dist: matplotlib; extra == "docs"
Requires-Dist: numpydoc; extra == "docs"
Requires-Dist: sphinx; extra == "docs"
Provides-Extra: tests
Requires-Dist: pytest; extra == "tests"
Requires-Dist: pytest-cov; extra == "tests"
Requires-Dist: pytest-xdist; extra == "tests"
